ts_topy/__init__.py
ts_topy/__main__.py
ts_topy/aliases.py
ts_topy/app.py
ts_topy/client.py
ts_topy/cluster_selector.py
ts_topy/models.py
ts_topy-0.5.0.dist-info/METADATA
ts_topy-0.5.0.dist-info/WHEEL
ts_topy-0.5.0.dist-info/entry_points.txt
ts_topy-0.5.0.dist-info/RECORD
