Metadata-Version: 2.4
Name: ts-topy
Version: 0.5.0
Summary: A Python-based monitoring tool for Teraslice distributed computing clusters
Author-email: Austin Godber <godber@gmail.com>
License: MIT
Requires-Python: >=3.10
Requires-Dist: httpx>=0.27.0
Requires-Dist: pydantic>=2.0.0
Requires-Dist: pyyaml>=6.0.0
Requires-Dist: textual>=0.47.0
Requires-Dist: typer>=0.12.0
